slrkit_utils/__init__.py
slrkit_utils/argument_parser.py
slrkit_utils/version.py
slrkit_utils-0.1.2.dist-info/LICENSE
slrkit_utils-0.1.2.dist-info/METADATA
slrkit_utils-0.1.2.dist-info/WHEEL
slrkit_utils-0.1.2.dist-info/top_level.txt
slrkit_utils-0.1.2.dist-info/RECORD
