Metadata-Version: 2.1
Name: slrkit-utils
Version: 0.1.2
Summary: Utility code for slr-kit projects
Home-page: https://github.com/robolab-pavia/slr-kit-utils
Author: Guido Benetti
Author-email: guido.benetti01@universitadipavia.it
License: GPL-3
Platform: UNKNOWN
Classifier: Programming Language :: Python :: 3
Classifier: Operating System :: OS Independent
License-File: LICENSE
